mrsdb2/__init__.py
mrsdb2/atomicwrite.py
mrsdb2/cache.py
mrsdb2/exceptions.py
mrsdb2/mrsdb.py
mrsdb2/utils.py
mrsdb2-2.3.1.dist-info/LICENSE
mrsdb2-2.3.1.dist-info/METADATA
mrsdb2-2.3.1.dist-info/WHEEL
mrsdb2-2.3.1.dist-info/top_level.txt
mrsdb2-2.3.1.dist-info/RECORD
