Metadata-Version: 2.1
Name: mrsdb2
Version: 2.3.1
Summary: The quick, rich, serverless, and efficient json-like Python 3 document database.
Home-page: https://github.com/netriza/mrsdb
Author: Netriza
Author-email: info@netriza.ml
License: UNKNOWN
Platform: UNKNOWN
Classifier: Programming Language :: Python :: 3
Classifier: License :: OSI Approved :: MIT License
Classifier: Operating System :: OS Independent
Classifier: Topic :: Database
Classifier: Topic :: Database :: Database Engines/Servers
Requires-Python: >=3.6
Requires-Dist: bson
Requires-Dist: bcrypt
Requires-Dist: requests
